{
  "timestamp": "2026-04-01T05:00:37.043741+00:00",
  "overall_score": -2.46,
  "classification": "MILD_BEARISH",
  "components": {
    "fear_greed": {
      "value": 8,
      "classification": "Extreme Fear",
      "normalized_score": -8.4,
      "trend": "declining",
      "yesterday": 11
    },
    "news": {
      "score": 0,
      "article_count": 0,
      "bullish_count": 0,
      "bearish_count": 0
    },
    "reddit": {
      "score": 1.5,
      "post_count": 25,
      "avg_upvote_ratio": 0.802,
      "weighted_text_avg": 0.096,
      "upvote_signal": 1.21
    }
  },
  "top_headlines": [],
  "top_reddit_posts": [
    "Daily Crypto Discussion - March 31, 2026 (GMT+0)",
    "Ethereum Had Zero Downtime in Its Entire Lifetime (10 Years), Here are its Competitors",
    "\u2018It\u2019s Happening\u2019\u2014Elon Musk Sparks Wild Bitcoin Price Speculation After Trump Declares \u2018Crypto Revolution\u2019",
    "Google Warns That Quantum Armageddon Is Drawing Closer",
    "92% Bitcoin Holders in Loss: CryptoQuant"
  ],
  "trading_signal": "CAUTION"
}